sflock/__init__.py
sflock/abstracts.py
sflock/auxiliary/__init__.py
sflock/auxiliary/decode_vbe_jse.py
sflock/config.py
sflock/data/7zz.elf
sflock/data/__init__.py
sflock/data/password.txt
sflock/data/poweriso.elf
sflock/data/win32/libmagic.dll
sflock/data/win32/magic.mgc
sflock/data/win32/regex2.dll
sflock/data/win32/zlib1.dll
sflock/data/win64/libgnurx-0.dll
sflock/data/win64/libmagic.dll
sflock/data/win64/magic.mgc
sflock/data/yara/archives.yar
sflock/data/yara/shellcodes.yar
sflock/data/zipjail.elf
sflock/decode/__init__.py
sflock/decode/office.py
sflock/exception.py
sflock/ident.py
sflock/main.py
sflock/misc.py
sflock/pick.py
sflock/unpack/__init__.py
sflock/unpack/ace.py
sflock/unpack/bup.py
sflock/unpack/cab.py
sflock/unpack/daa.py
sflock/unpack/eml.py
sflock/unpack/lzip.py
sflock/unpack/msg.py
sflock/unpack/mso.py
sflock/unpack/office.py
sflock/unpack/pdf.py
sflock/unpack/pgp.py
sflock/unpack/rar.py
sflock/unpack/tar.py
sflock/unpack/zip7.py
sflock/unpack/zpaq.py
sflock2-0.3.85.dist-info/METADATA
sflock2-0.3.85.dist-info/WHEEL
sflock2-0.3.85.dist-info/entry_points.txt
sflock2-0.3.85.dist-info/RECORD
