Metadata-Version: 2.4
Name: SFlock2
Version: 0.3.85
Summary: Sample staging and detonation utility
License: GPL-3.0-only
Keywords: sflock,unarchive
Author: Hatching B.V.
Author-email: jbr@hatching.io
Requires-Python: >=3.10,<4.0
Classifier: License :: OSI Approved :: GNU General Public License v3 (GPLv3)
Classifier: Programming Language :: Python :: 3
Classifier: Programming Language :: Python :: 3.10
Classifier: Programming Language :: Python :: 3.11
Classifier: Programming Language :: Python :: 3.12
Classifier: Programming Language :: Python :: 3.13
Classifier: Programming Language :: Python :: 3.14
Provides-Extra: linux
Provides-Extra: shellcode
Provides-Extra: windows
Requires-Dist: click
Requires-Dist: cryptography (>=44.0.0)
Requires-Dist: olefile (>=0.43)
Requires-Dist: pefile
Requires-Dist: python-dateutil
Requires-Dist: python-magic (>=0.4.13) ; (sys_platform == "linux") and (extra == "linux")
Requires-Dist: python-magic-bin (>=0.4.14) ; (sys_platform == "win32") and (extra == "windows")
Requires-Dist: unicorn (>=2.0.0) ; extra == "shellcode"
Requires-Dist: yara-python (>=4.1.0) ; extra == "shellcode"
